{"dependencies":[{"name":"/home/melvin/PhpstormProjects/gjx/package.json","includedInParent":true,"mtime":1528375847532},{"name":"/home/melvin/PhpstormProjects/gjx/.babelrc","includedInParent":true,"mtime":1528358458908},{"name":"/home/melvin/PhpstormProjects/gjx/node_modules/pixi.js/package.json","includedInParent":true,"mtime":1528375667214},{"name":"earcut","loc":{"line":6,"column":22}},{"name":"./buildLine","loc":{"line":10,"column":25}},{"name":"../../../utils","loc":{"line":14,"column":21}}],"generated":{"js":"'use strict';\n\nexports.__esModule = true;\nexports.default = buildRoundedRectangle;\n\nvar _earcut = require('earcut');\n\nvar _earcut2 = _interopRequireDefault(_earcut);\n\nvar _buildLine = require('./buildLine');\n\nvar _buildLine2 = _interopRequireDefault(_buildLine);\n\nvar _utils = require('../../../utils');\n\nfunction _interopRequireDefault(obj) { return obj && obj.__esModule ? obj : { default: obj }; }\n\n/**\n * Builds a rounded rectangle to draw\n *\n * Ignored from docs since it is not directly exposed.\n *\n * @ignore\n * @private\n * @param {PIXI.WebGLGraphicsData} graphicsData - The graphics object containing all the necessary properties\n * @param {object} webGLData - an object containing all the webGL-specific information to create this shape\n * @param {object} webGLDataNativeLines - an object containing all the webGL-specific information to create nativeLines\n */\nfunction buildRoundedRectangle(graphicsData, webGLData, webGLDataNativeLines) {\n    var rrectData = graphicsData.shape;\n    var x = rrectData.x;\n    var y = rrectData.y;\n    var width = rrectData.width;\n    var height = rrectData.height;\n\n    var radius = rrectData.radius;\n\n    var recPoints = [];\n\n    recPoints.push(x, y + radius);\n    quadraticBezierCurve(x, y + height - radius, x, y + height, x + radius, y + height, recPoints);\n    quadraticBezierCurve(x + width - radius, y + height, x + width, y + height, x + width, y + height - radius, recPoints);\n    quadraticBezierCurve(x + width, y + radius, x + width, y, x + width - radius, y, recPoints);\n    quadraticBezierCurve(x + radius, y, x, y, x, y + radius + 0.0000000001, recPoints);\n\n    // this tiny number deals with the issue that occurs when points overlap and earcut fails to triangulate the item.\n    // TODO - fix this properly, this is not very elegant.. but it works for now.\n\n    if (graphicsData.fill) {\n        var color = (0, _utils.hex2rgb)(graphicsData.fillColor);\n        var alpha = graphicsData.fillAlpha;\n\n        var r = color[0] * alpha;\n        var g = color[1] * alpha;\n        var b = color[2] * alpha;\n\n        var verts = webGLData.points;\n        var indices = webGLData.indices;\n\n        var vecPos = verts.length / 6;\n\n        var triangles = (0, _earcut2.default)(recPoints, null, 2);\n\n        for (var i = 0, j = triangles.length; i < j; i += 3) {\n            indices.push(triangles[i] + vecPos);\n            indices.push(triangles[i] + vecPos);\n            indices.push(triangles[i + 1] + vecPos);\n            indices.push(triangles[i + 2] + vecPos);\n            indices.push(triangles[i + 2] + vecPos);\n        }\n\n        for (var _i = 0, _j = recPoints.length; _i < _j; _i++) {\n            verts.push(recPoints[_i], recPoints[++_i], r, g, b, alpha);\n        }\n    }\n\n    if (graphicsData.lineWidth) {\n        var tempPoints = graphicsData.points;\n\n        graphicsData.points = recPoints;\n\n        (0, _buildLine2.default)(graphicsData, webGLData, webGLDataNativeLines);\n\n        graphicsData.points = tempPoints;\n    }\n}\n\n/**\n * Calculate a single point for a quadratic bezier curve.\n * Utility function used by quadraticBezierCurve.\n * Ignored from docs since it is not directly exposed.\n *\n * @ignore\n * @private\n * @param {number} n1 - first number\n * @param {number} n2 - second number\n * @param {number} perc - percentage\n * @return {number} the result\n *\n */\nfunction getPt(n1, n2, perc) {\n    var diff = n2 - n1;\n\n    return n1 + diff * perc;\n}\n\n/**\n * Calculate the points for a quadratic bezier curve. (helper function..)\n * Based on: https://stackoverflow.com/questions/785097/how-do-i-implement-a-bezier-curve-in-c\n *\n * Ignored from docs since it is not directly exposed.\n *\n * @ignore\n * @private\n * @param {number} fromX - Origin point x\n * @param {number} fromY - Origin point x\n * @param {number} cpX - Control point x\n * @param {number} cpY - Control point y\n * @param {number} toX - Destination point x\n * @param {number} toY - Destination point y\n * @param {number[]} [out=[]] - The output array to add points into. If not passed, a new array is created.\n * @return {number[]} an array of points\n */\nfunction quadraticBezierCurve(fromX, fromY, cpX, cpY, toX, toY) {\n    var out = arguments.length > 6 && arguments[6] !== undefined ? arguments[6] : [];\n\n    var n = 20;\n    var points = out;\n\n    var xa = 0;\n    var ya = 0;\n    var xb = 0;\n    var yb = 0;\n    var x = 0;\n    var y = 0;\n\n    for (var i = 0, j = 0; i <= n; ++i) {\n        j = i / n;\n\n        // The Green Line\n        xa = getPt(fromX, cpX, j);\n        ya = getPt(fromY, cpY, j);\n        xb = getPt(cpX, toX, j);\n        yb = getPt(cpY, toY, j);\n\n        // The Black Dot\n        x = getPt(xa, xb, j);\n        y = getPt(ya, yb, j);\n\n        points.push(x, y);\n    }\n\n    return points;\n}\n//# sourceMappingURL=buildRoundedRectangle.js.map","map":{"mappings":[{"source":"node_modules/pixi.js/lib/core/graphics/webgl/utils/buildRoundedRectangle.js","original":{"line":1,"column":0},"generated":{"line":1,"column":0}},{"source":"node_modules/pixi.js/lib/core/graphics/webgl/utils/buildRoundedRectangle.js","original":{"line":2,"column":0},"generated":{"line":2,"column":0}},{"source":"node_modules/pixi.js/lib/core/graphics/webgl/utils/buildRoundedRectangle.js","original":{"line":3,"column":0},"generated":{"line":3,"column":0}},{"source":"node_modules/pixi.js/lib/core/graphics/webgl/utils/buildRoundedRectangle.js","original":{"line":4,"column":0},"generated":{"line":4,"column":0}},{"source":"node_modules/pixi.js/lib/core/graphics/webgl/utils/buildRoundedRectangle.js","original":{"line":5,"column":0},"generated":{"line":5,"column":0}},{"source":"node_modules/pixi.js/lib/core/graphics/webgl/utils/buildRoundedRectangle.js","original":{"line":6,"column":0},"generated":{"line":6,"column":0}},{"source":"node_modules/pixi.js/lib/core/graphics/webgl/utils/buildRoundedRectangle.js","original":{"line":7,"column":0},"generated":{"line":7,"column":0}},{"source":"node_modules/pixi.js/lib/core/graphics/webgl/utils/buildRoundedRectangle.js","original":{"line":8,"column":0},"generated":{"line":8,"column":0}},{"source":"node_modules/pixi.js/lib/core/graphics/webgl/utils/buildRoundedRectangle.js","original":{"line":9,"column":0},"generated":{"line":9,"column":0}},{"source":"node_modules/pixi.js/lib/core/graphics/webgl/utils/buildRoundedRectangle.js","original":{"line":10,"column":0},"generated":{"line":10,"column":0}},{"source":"node_modules/pixi.js/lib/core/graphics/webgl/utils/buildRoundedRectangle.js","original":{"line":11,"column":0},"generated":{"line":11,"column":0}},{"source":"node_modules/pixi.js/lib/core/graphics/webgl/utils/buildRoundedRectangle.js","original":{"line":12,"column":0},"generated":{"line":12,"column":0}},{"source":"node_modules/pixi.js/lib/core/graphics/webgl/utils/buildRoundedRectangle.js","original":{"line":13,"column":0},"generated":{"line":13,"column":0}},{"source":"node_modules/pixi.js/lib/core/graphics/webgl/utils/buildRoundedRectangle.js","original":{"line":14,"column":0},"generated":{"line":14,"column":0}},{"source":"node_modules/pixi.js/lib/core/graphics/webgl/utils/buildRoundedRectangle.js","original":{"line":15,"column":0},"generated":{"line":15,"column":0}},{"source":"node_modules/pixi.js/lib/core/graphics/webgl/utils/buildRoundedRectangle.js","original":{"line":16,"column":0},"generated":{"line":16,"column":0}},{"source":"node_modules/pixi.js/lib/core/graphics/webgl/utils/buildRoundedRectangle.js","original":{"line":17,"column":0},"generated":{"line":17,"column":0}},{"source":"node_modules/pixi.js/lib/core/graphics/webgl/utils/buildRoundedRectangle.js","original":{"line":18,"column":0},"generated":{"line":18,"column":0}},{"source":"node_modules/pixi.js/lib/core/graphics/webgl/utils/buildRoundedRectangle.js","original":{"line":19,"column":0},"generated":{"line":19,"column":0}},{"source":"node_modules/pixi.js/lib/core/graphics/webgl/utils/buildRoundedRectangle.js","original":{"line":20,"column":0},"generated":{"line":20,"column":0}},{"source":"node_modules/pixi.js/lib/core/graphics/webgl/utils/buildRoundedRectangle.js","original":{"line":21,"column":0},"generated":{"line":21,"column":0}},{"source":"node_modules/pixi.js/lib/core/graphics/webgl/utils/buildRoundedRectangle.js","original":{"line":22,"column":0},"generated":{"line":22,"column":0}},{"source":"node_modules/pixi.js/lib/core/graphics/webgl/utils/buildRoundedRectangle.js","original":{"line":23,"column":0},"generated":{"line":23,"column":0}},{"source":"node_modules/pixi.js/lib/core/graphics/webgl/utils/buildRoundedRectangle.js","original":{"line":24,"column":0},"generated":{"line":24,"column":0}},{"source":"node_modules/pixi.js/lib/core/graphics/webgl/utils/buildRoundedRectangle.js","original":{"line":25,"column":0},"generated":{"line":25,"column":0}},{"source":"node_modules/pixi.js/lib/core/graphics/webgl/utils/buildRoundedRectangle.js","original":{"line":26,"column":0},"generated":{"line":26,"column":0}},{"source":"node_modules/pixi.js/lib/core/graphics/webgl/utils/buildRoundedRectangle.js","original":{"line":27,"column":0},"generated":{"line":27,"column":0}},{"source":"node_modules/pixi.js/lib/core/graphics/webgl/utils/buildRoundedRectangle.js","original":{"line":28,"column":0},"generated":{"line":28,"column":0}},{"source":"node_modules/pixi.js/lib/core/graphics/webgl/utils/buildRoundedRectangle.js","original":{"line":29,"column":0},"generated":{"line":29,"column":0}},{"source":"node_modules/pixi.js/lib/core/graphics/webgl/utils/buildRoundedRectangle.js","original":{"line":30,"column":0},"generated":{"line":30,"column":0}},{"source":"node_modules/pixi.js/lib/core/graphics/webgl/utils/buildRoundedRectangle.js","original":{"line":31,"column":0},"generated":{"line":31,"column":0}},{"source":"node_modules/pixi.js/lib/core/graphics/webgl/utils/buildRoundedRectangle.js","original":{"line":32,"column":0},"generated":{"line":32,"column":0}},{"source":"node_modules/pixi.js/lib/core/graphics/webgl/utils/buildRoundedRectangle.js","original":{"line":33,"column":0},"generated":{"line":33,"column":0}},{"source":"node_modules/pixi.js/lib/core/graphics/webgl/utils/buildRoundedRectangle.js","original":{"line":34,"column":0},"generated":{"line":34,"column":0}},{"source":"node_modules/pixi.js/lib/core/graphics/webgl/utils/buildRoundedRectangle.js","original":{"line":35,"column":0},"generated":{"line":35,"column":0}},{"source":"node_modules/pixi.js/lib/core/graphics/webgl/utils/buildRoundedRectangle.js","original":{"line":36,"column":0},"generated":{"line":36,"column":0}},{"source":"node_modules/pixi.js/lib/core/graphics/webgl/utils/buildRoundedRectangle.js","original":{"line":37,"column":0},"generated":{"line":37,"column":0}},{"source":"node_modules/pixi.js/lib/core/graphics/webgl/utils/buildRoundedRectangle.js","original":{"line":38,"column":0},"generated":{"line":38,"column":0}},{"source":"node_modules/pixi.js/lib/core/graphics/webgl/utils/buildRoundedRectangle.js","original":{"line":39,"column":0},"generated":{"line":39,"column":0}},{"source":"node_modules/pixi.js/lib/core/graphics/webgl/utils/buildRoundedRectangle.js","original":{"line":40,"column":0},"generated":{"line":40,"column":0}},{"source":"node_modules/pixi.js/lib/core/graphics/webgl/utils/buildRoundedRectangle.js","original":{"line":41,"column":0},"generated":{"line":41,"column":0}},{"source":"node_modules/pixi.js/lib/core/graphics/webgl/utils/buildRoundedRectangle.js","original":{"line":42,"column":0},"generated":{"line":42,"column":0}},{"source":"node_modules/pixi.js/lib/core/graphics/webgl/utils/buildRoundedRectangle.js","original":{"line":43,"column":0},"generated":{"line":43,"column":0}},{"source":"node_modules/pixi.js/lib/core/graphics/webgl/utils/buildRoundedRectangle.js","original":{"line":44,"column":0},"generated":{"line":44,"column":0}},{"source":"node_modules/pixi.js/lib/core/graphics/webgl/utils/buildRoundedRectangle.js","original":{"line":45,"column":0},"generated":{"line":45,"column":0}},{"source":"node_modules/pixi.js/lib/core/graphics/webgl/utils/buildRoundedRectangle.js","original":{"line":46,"column":0},"generated":{"line":46,"column":0}},{"source":"node_modules/pixi.js/lib/core/graphics/webgl/utils/buildRoundedRectangle.js","original":{"line":47,"column":0},"generated":{"line":47,"column":0}},{"source":"node_modules/pixi.js/lib/core/graphics/webgl/utils/buildRoundedRectangle.js","original":{"line":48,"column":0},"generated":{"line":48,"column":0}},{"source":"node_modules/pixi.js/lib/core/graphics/webgl/utils/buildRoundedRectangle.js","original":{"line":49,"column":0},"generated":{"line":49,"column":0}},{"source":"node_modules/pixi.js/lib/core/graphics/webgl/utils/buildRoundedRectangle.js","original":{"line":50,"column":0},"generated":{"line":50,"column":0}},{"source":"node_modules/pixi.js/lib/core/graphics/webgl/utils/buildRoundedRectangle.js","original":{"line":51,"column":0},"generated":{"line":51,"column":0}},{"source":"node_modules/pixi.js/lib/core/graphics/webgl/utils/buildRoundedRectangle.js","original":{"line":52,"column":0},"generated":{"line":52,"column":0}},{"source":"node_modules/pixi.js/lib/core/graphics/webgl/utils/buildRoundedRectangle.js","original":{"line":53,"column":0},"generated":{"line":53,"column":0}},{"source":"node_modules/pixi.js/lib/core/graphics/webgl/utils/buildRoundedRectangle.js","original":{"line":54,"column":0},"generated":{"line":54,"column":0}},{"source":"node_modules/pixi.js/lib/core/graphics/webgl/utils/buildRoundedRectangle.js","original":{"line":55,"column":0},"generated":{"line":55,"column":0}},{"source":"node_modules/pixi.js/lib/core/graphics/webgl/utils/buildRoundedRectangle.js","original":{"line":56,"column":0},"generated":{"line":56,"column":0}},{"source":"node_modules/pixi.js/lib/core/graphics/webgl/utils/buildRoundedRectangle.js","original":{"line":57,"column":0},"generated":{"line":57,"column":0}},{"source":"node_modules/pixi.js/lib/core/graphics/webgl/utils/buildRoundedRectangle.js","original":{"line":58,"column":0},"generated":{"line":58,"column":0}},{"source":"node_modules/pixi.js/lib/core/graphics/webgl/utils/buildRoundedRectangle.js","original":{"line":59,"column":0},"generated":{"line":59,"column":0}},{"source":"node_modules/pixi.js/lib/core/graphics/webgl/utils/buildRoundedRectangle.js","original":{"line":60,"column":0},"generated":{"line":60,"column":0}},{"source":"node_modules/pixi.js/lib/core/graphics/webgl/utils/buildRoundedRectangle.js","original":{"line":61,"column":0},"generated":{"line":61,"column":0}},{"source":"node_modules/pixi.js/lib/core/graphics/webgl/utils/buildRoundedRectangle.js","original":{"line":62,"column":0},"generated":{"line":62,"column":0}},{"source":"node_modules/pixi.js/lib/core/graphics/webgl/utils/buildRoundedRectangle.js","original":{"line":63,"column":0},"generated":{"line":63,"column":0}},{"source":"node_modules/pixi.js/lib/core/graphics/webgl/utils/buildRoundedRectangle.js","original":{"line":64,"column":0},"generated":{"line":64,"column":0}},{"source":"node_modules/pixi.js/lib/core/graphics/webgl/utils/buildRoundedRectangle.js","original":{"line":65,"column":0},"generated":{"line":65,"column":0}},{"source":"node_modules/pixi.js/lib/core/graphics/webgl/utils/buildRoundedRectangle.js","original":{"line":66,"column":0},"generated":{"line":66,"column":0}},{"source":"node_modules/pixi.js/lib/core/graphics/webgl/utils/buildRoundedRectangle.js","original":{"line":67,"column":0},"generated":{"line":67,"column":0}},{"source":"node_modules/pixi.js/lib/core/graphics/webgl/utils/buildRoundedRectangle.js","original":{"line":68,"column":0},"generated":{"line":68,"column":0}},{"source":"node_modules/pixi.js/lib/core/graphics/webgl/utils/buildRoundedRectangle.js","original":{"line":69,"column":0},"generated":{"line":69,"column":0}},{"source":"node_modules/pixi.js/lib/core/graphics/webgl/utils/buildRoundedRectangle.js","original":{"line":70,"column":0},"generated":{"line":70,"column":0}},{"source":"node_modules/pixi.js/lib/core/graphics/webgl/utils/buildRoundedRectangle.js","original":{"line":71,"column":0},"generated":{"line":71,"column":0}},{"source":"node_modules/pixi.js/lib/core/graphics/webgl/utils/buildRoundedRectangle.js","original":{"line":72,"column":0},"generated":{"line":72,"column":0}},{"source":"node_modules/pixi.js/lib/core/graphics/webgl/utils/buildRoundedRectangle.js","original":{"line":73,"column":0},"generated":{"line":73,"column":0}},{"source":"node_modules/pixi.js/lib/core/graphics/webgl/utils/buildRoundedRectangle.js","original":{"line":74,"column":0},"generated":{"line":74,"column":0}},{"source":"node_modules/pixi.js/lib/core/graphics/webgl/utils/buildRoundedRectangle.js","original":{"line":75,"column":0},"generated":{"line":75,"column":0}},{"source":"node_modules/pixi.js/lib/core/graphics/webgl/utils/buildRoundedRectangle.js","original":{"line":76,"column":0},"generated":{"line":76,"column":0}},{"source":"node_modules/pixi.js/lib/core/graphics/webgl/utils/buildRoundedRectangle.js","original":{"line":77,"column":0},"generated":{"line":77,"column":0}},{"source":"node_modules/pixi.js/lib/core/graphics/webgl/utils/buildRoundedRectangle.js","original":{"line":78,"column":0},"generated":{"line":78,"column":0}},{"source":"node_modules/pixi.js/lib/core/graphics/webgl/utils/buildRoundedRectangle.js","original":{"line":79,"column":0},"generated":{"line":79,"column":0}},{"source":"node_modules/pixi.js/lib/core/graphics/webgl/utils/buildRoundedRectangle.js","original":{"line":80,"column":0},"generated":{"line":80,"column":0}},{"source":"node_modules/pixi.js/lib/core/graphics/webgl/utils/buildRoundedRectangle.js","original":{"line":81,"column":0},"generated":{"line":81,"column":0}},{"source":"node_modules/pixi.js/lib/core/graphics/webgl/utils/buildRoundedRectangle.js","original":{"line":82,"column":0},"generated":{"line":82,"column":0}},{"source":"node_modules/pixi.js/lib/core/graphics/webgl/utils/buildRoundedRectangle.js","original":{"line":83,"column":0},"generated":{"line":83,"column":0}},{"source":"node_modules/pixi.js/lib/core/graphics/webgl/utils/buildRoundedRectangle.js","original":{"line":84,"column":0},"generated":{"line":84,"column":0}},{"source":"node_modules/pixi.js/lib/core/graphics/webgl/utils/buildRoundedRectangle.js","original":{"line":85,"column":0},"generated":{"line":85,"column":0}},{"source":"node_modules/pixi.js/lib/core/graphics/webgl/utils/buildRoundedRectangle.js","original":{"line":86,"column":0},"generated":{"line":86,"column":0}},{"source":"node_modules/pixi.js/lib/core/graphics/webgl/utils/buildRoundedRectangle.js","original":{"line":87,"column":0},"generated":{"line":87,"column":0}},{"source":"node_modules/pixi.js/lib/core/graphics/webgl/utils/buildRoundedRectangle.js","original":{"line":88,"column":0},"generated":{"line":88,"column":0}},{"source":"node_modules/pixi.js/lib/core/graphics/webgl/utils/buildRoundedRectangle.js","original":{"line":89,"column":0},"generated":{"line":89,"column":0}},{"source":"node_modules/pixi.js/lib/core/graphics/webgl/utils/buildRoundedRectangle.js","original":{"line":90,"column":0},"generated":{"line":90,"column":0}},{"source":"node_modules/pixi.js/lib/core/graphics/webgl/utils/buildRoundedRectangle.js","original":{"line":91,"column":0},"generated":{"line":91,"column":0}},{"source":"node_modules/pixi.js/lib/core/graphics/webgl/utils/buildRoundedRectangle.js","original":{"line":92,"column":0},"generated":{"line":92,"column":0}},{"source":"node_modules/pixi.js/lib/core/graphics/webgl/utils/buildRoundedRectangle.js","original":{"line":93,"column":0},"generated":{"line":93,"column":0}},{"source":"node_modules/pixi.js/lib/core/graphics/webgl/utils/buildRoundedRectangle.js","original":{"line":94,"column":0},"generated":{"line":94,"column":0}},{"source":"node_modules/pixi.js/lib/core/graphics/webgl/utils/buildRoundedRectangle.js","original":{"line":95,"column":0},"generated":{"line":95,"column":0}},{"source":"node_modules/pixi.js/lib/core/graphics/webgl/utils/buildRoundedRectangle.js","original":{"line":96,"column":0},"generated":{"line":96,"column":0}},{"source":"node_modules/pixi.js/lib/core/graphics/webgl/utils/buildRoundedRectangle.js","original":{"line":97,"column":0},"generated":{"line":97,"column":0}},{"source":"node_modules/pixi.js/lib/core/graphics/webgl/utils/buildRoundedRectangle.js","original":{"line":98,"column":0},"generated":{"line":98,"column":0}},{"source":"node_modules/pixi.js/lib/core/graphics/webgl/utils/buildRoundedRectangle.js","original":{"line":99,"column":0},"generated":{"line":99,"column":0}},{"source":"node_modules/pixi.js/lib/core/graphics/webgl/utils/buildRoundedRectangle.js","original":{"line":100,"column":0},"generated":{"line":100,"column":0}},{"source":"node_modules/pixi.js/lib/core/graphics/webgl/utils/buildRoundedRectangle.js","original":{"line":101,"column":0},"generated":{"line":101,"column":0}},{"source":"node_modules/pixi.js/lib/core/graphics/webgl/utils/buildRoundedRectangle.js","original":{"line":102,"column":0},"generated":{"line":102,"column":0}},{"source":"node_modules/pixi.js/lib/core/graphics/webgl/utils/buildRoundedRectangle.js","original":{"line":103,"column":0},"generated":{"line":103,"column":0}},{"source":"node_modules/pixi.js/lib/core/graphics/webgl/utils/buildRoundedRectangle.js","original":{"line":104,"column":0},"generated":{"line":104,"column":0}},{"source":"node_modules/pixi.js/lib/core/graphics/webgl/utils/buildRoundedRectangle.js","original":{"line":105,"column":0},"generated":{"line":105,"column":0}},{"source":"node_modules/pixi.js/lib/core/graphics/webgl/utils/buildRoundedRectangle.js","original":{"line":106,"column":0},"generated":{"line":106,"column":0}},{"source":"node_modules/pixi.js/lib/core/graphics/webgl/utils/buildRoundedRectangle.js","original":{"line":107,"column":0},"generated":{"line":107,"column":0}},{"source":"node_modules/pixi.js/lib/core/graphics/webgl/utils/buildRoundedRectangle.js","original":{"line":108,"column":0},"generated":{"line":108,"column":0}},{"source":"node_modules/pixi.js/lib/core/graphics/webgl/utils/buildRoundedRectangle.js","original":{"line":109,"column":0},"generated":{"line":109,"column":0}},{"source":"node_modules/pixi.js/lib/core/graphics/webgl/utils/buildRoundedRectangle.js","original":{"line":110,"column":0},"generated":{"line":110,"column":0}},{"source":"node_modules/pixi.js/lib/core/graphics/webgl/utils/buildRoundedRectangle.js","original":{"line":111,"column":0},"generated":{"line":111,"column":0}},{"source":"node_modules/pixi.js/lib/core/graphics/webgl/utils/buildRoundedRectangle.js","original":{"line":112,"column":0},"generated":{"line":112,"column":0}},{"source":"node_modules/pixi.js/lib/core/graphics/webgl/utils/buildRoundedRectangle.js","original":{"line":113,"column":0},"generated":{"line":113,"column":0}},{"source":"node_modules/pixi.js/lib/core/graphics/webgl/utils/buildRoundedRectangle.js","original":{"line":114,"column":0},"generated":{"line":114,"column":0}},{"source":"node_modules/pixi.js/lib/core/graphics/webgl/utils/buildRoundedRectangle.js","original":{"line":115,"column":0},"generated":{"line":115,"column":0}},{"source":"node_modules/pixi.js/lib/core/graphics/webgl/utils/buildRoundedRectangle.js","original":{"line":116,"column":0},"generated":{"line":116,"column":0}},{"source":"node_modules/pixi.js/lib/core/graphics/webgl/utils/buildRoundedRectangle.js","original":{"line":117,"column":0},"generated":{"line":117,"column":0}},{"source":"node_modules/pixi.js/lib/core/graphics/webgl/utils/buildRoundedRectangle.js","original":{"line":118,"column":0},"generated":{"line":118,"column":0}},{"source":"node_modules/pixi.js/lib/core/graphics/webgl/utils/buildRoundedRectangle.js","original":{"line":119,"column":0},"generated":{"line":119,"column":0}},{"source":"node_modules/pixi.js/lib/core/graphics/webgl/utils/buildRoundedRectangle.js","original":{"line":120,"column":0},"generated":{"line":120,"column":0}},{"source":"node_modules/pixi.js/lib/core/graphics/webgl/utils/buildRoundedRectangle.js","original":{"line":121,"column":0},"generated":{"line":121,"column":0}},{"source":"node_modules/pixi.js/lib/core/graphics/webgl/utils/buildRoundedRectangle.js","original":{"line":122,"column":0},"generated":{"line":122,"column":0}},{"source":"node_modules/pixi.js/lib/core/graphics/webgl/utils/buildRoundedRectangle.js","original":{"line":123,"column":0},"generated":{"line":123,"column":0}},{"source":"node_modules/pixi.js/lib/core/graphics/webgl/utils/buildRoundedRectangle.js","original":{"line":124,"column":0},"generated":{"line":124,"column":0}},{"source":"node_modules/pixi.js/lib/core/graphics/webgl/utils/buildRoundedRectangle.js","original":{"line":125,"column":0},"generated":{"line":125,"column":0}},{"source":"node_modules/pixi.js/lib/core/graphics/webgl/utils/buildRoundedRectangle.js","original":{"line":126,"column":0},"generated":{"line":126,"column":0}},{"source":"node_modules/pixi.js/lib/core/graphics/webgl/utils/buildRoundedRectangle.js","original":{"line":127,"column":0},"generated":{"line":127,"column":0}},{"source":"node_modules/pixi.js/lib/core/graphics/webgl/utils/buildRoundedRectangle.js","original":{"line":128,"column":0},"generated":{"line":128,"column":0}},{"source":"node_modules/pixi.js/lib/core/graphics/webgl/utils/buildRoundedRectangle.js","original":{"line":129,"column":0},"generated":{"line":129,"column":0}},{"source":"node_modules/pixi.js/lib/core/graphics/webgl/utils/buildRoundedRectangle.js","original":{"line":130,"column":0},"generated":{"line":130,"column":0}},{"source":"node_modules/pixi.js/lib/core/graphics/webgl/utils/buildRoundedRectangle.js","original":{"line":131,"column":0},"generated":{"line":131,"column":0}},{"source":"node_modules/pixi.js/lib/core/graphics/webgl/utils/buildRoundedRectangle.js","original":{"line":132,"column":0},"generated":{"line":132,"column":0}},{"source":"node_modules/pixi.js/lib/core/graphics/webgl/utils/buildRoundedRectangle.js","original":{"line":133,"column":0},"generated":{"line":133,"column":0}},{"source":"node_modules/pixi.js/lib/core/graphics/webgl/utils/buildRoundedRectangle.js","original":{"line":134,"column":0},"generated":{"line":134,"column":0}},{"source":"node_modules/pixi.js/lib/core/graphics/webgl/utils/buildRoundedRectangle.js","original":{"line":135,"column":0},"generated":{"line":135,"column":0}},{"source":"node_modules/pixi.js/lib/core/graphics/webgl/utils/buildRoundedRectangle.js","original":{"line":136,"column":0},"generated":{"line":136,"column":0}},{"source":"node_modules/pixi.js/lib/core/graphics/webgl/utils/buildRoundedRectangle.js","original":{"line":137,"column":0},"generated":{"line":137,"column":0}},{"source":"node_modules/pixi.js/lib/core/graphics/webgl/utils/buildRoundedRectangle.js","original":{"line":138,"column":0},"generated":{"line":138,"column":0}},{"source":"node_modules/pixi.js/lib/core/graphics/webgl/utils/buildRoundedRectangle.js","original":{"line":139,"column":0},"generated":{"line":139,"column":0}},{"source":"node_modules/pixi.js/lib/core/graphics/webgl/utils/buildRoundedRectangle.js","original":{"line":140,"column":0},"generated":{"line":140,"column":0}},{"source":"node_modules/pixi.js/lib/core/graphics/webgl/utils/buildRoundedRectangle.js","original":{"line":141,"column":0},"generated":{"line":141,"column":0}},{"source":"node_modules/pixi.js/lib/core/graphics/webgl/utils/buildRoundedRectangle.js","original":{"line":142,"column":0},"generated":{"line":142,"column":0}},{"source":"node_modules/pixi.js/lib/core/graphics/webgl/utils/buildRoundedRectangle.js","original":{"line":143,"column":0},"generated":{"line":143,"column":0}},{"source":"node_modules/pixi.js/lib/core/graphics/webgl/utils/buildRoundedRectangle.js","original":{"line":144,"column":0},"generated":{"line":144,"column":0}},{"source":"node_modules/pixi.js/lib/core/graphics/webgl/utils/buildRoundedRectangle.js","original":{"line":145,"column":0},"generated":{"line":145,"column":0}},{"source":"node_modules/pixi.js/lib/core/graphics/webgl/utils/buildRoundedRectangle.js","original":{"line":146,"column":0},"generated":{"line":146,"column":0}},{"source":"node_modules/pixi.js/lib/core/graphics/webgl/utils/buildRoundedRectangle.js","original":{"line":147,"column":0},"generated":{"line":147,"column":0}},{"source":"node_modules/pixi.js/lib/core/graphics/webgl/utils/buildRoundedRectangle.js","original":{"line":148,"column":0},"generated":{"line":148,"column":0}},{"source":"node_modules/pixi.js/lib/core/graphics/webgl/utils/buildRoundedRectangle.js","original":{"line":149,"column":0},"generated":{"line":149,"column":0}},{"source":"node_modules/pixi.js/lib/core/graphics/webgl/utils/buildRoundedRectangle.js","original":{"line":150,"column":0},"generated":{"line":150,"column":0}},{"source":"node_modules/pixi.js/lib/core/graphics/webgl/utils/buildRoundedRectangle.js","original":{"line":151,"column":0},"generated":{"line":151,"column":0}},{"source":"node_modules/pixi.js/lib/core/graphics/webgl/utils/buildRoundedRectangle.js","original":{"line":152,"column":0},"generated":{"line":152,"column":0}},{"source":"node_modules/pixi.js/lib/core/graphics/webgl/utils/buildRoundedRectangle.js","original":{"line":153,"column":0},"generated":{"line":153,"column":0}},{"source":"node_modules/pixi.js/lib/core/graphics/webgl/utils/buildRoundedRectangle.js","original":{"line":154,"column":0},"generated":{"line":154,"column":0}},{"source":"node_modules/pixi.js/lib/core/graphics/webgl/utils/buildRoundedRectangle.js","original":{"line":155,"column":0},"generated":{"line":155,"column":0}}],"sources":{"node_modules/pixi.js/lib/core/graphics/webgl/utils/buildRoundedRectangle.js":"'use strict';\n\nexports.__esModule = true;\nexports.default = buildRoundedRectangle;\n\nvar _earcut = require('earcut');\n\nvar _earcut2 = _interopRequireDefault(_earcut);\n\nvar _buildLine = require('./buildLine');\n\nvar _buildLine2 = _interopRequireDefault(_buildLine);\n\nvar _utils = require('../../../utils');\n\nfunction _interopRequireDefault(obj) { return obj && obj.__esModule ? obj : { default: obj }; }\n\n/**\n * Builds a rounded rectangle to draw\n *\n * Ignored from docs since it is not directly exposed.\n *\n * @ignore\n * @private\n * @param {PIXI.WebGLGraphicsData} graphicsData - The graphics object containing all the necessary properties\n * @param {object} webGLData - an object containing all the webGL-specific information to create this shape\n * @param {object} webGLDataNativeLines - an object containing all the webGL-specific information to create nativeLines\n */\nfunction buildRoundedRectangle(graphicsData, webGLData, webGLDataNativeLines) {\n    var rrectData = graphicsData.shape;\n    var x = rrectData.x;\n    var y = rrectData.y;\n    var width = rrectData.width;\n    var height = rrectData.height;\n\n    var radius = rrectData.radius;\n\n    var recPoints = [];\n\n    recPoints.push(x, y + radius);\n    quadraticBezierCurve(x, y + height - radius, x, y + height, x + radius, y + height, recPoints);\n    quadraticBezierCurve(x + width - radius, y + height, x + width, y + height, x + width, y + height - radius, recPoints);\n    quadraticBezierCurve(x + width, y + radius, x + width, y, x + width - radius, y, recPoints);\n    quadraticBezierCurve(x + radius, y, x, y, x, y + radius + 0.0000000001, recPoints);\n\n    // this tiny number deals with the issue that occurs when points overlap and earcut fails to triangulate the item.\n    // TODO - fix this properly, this is not very elegant.. but it works for now.\n\n    if (graphicsData.fill) {\n        var color = (0, _utils.hex2rgb)(graphicsData.fillColor);\n        var alpha = graphicsData.fillAlpha;\n\n        var r = color[0] * alpha;\n        var g = color[1] * alpha;\n        var b = color[2] * alpha;\n\n        var verts = webGLData.points;\n        var indices = webGLData.indices;\n\n        var vecPos = verts.length / 6;\n\n        var triangles = (0, _earcut2.default)(recPoints, null, 2);\n\n        for (var i = 0, j = triangles.length; i < j; i += 3) {\n            indices.push(triangles[i] + vecPos);\n            indices.push(triangles[i] + vecPos);\n            indices.push(triangles[i + 1] + vecPos);\n            indices.push(triangles[i + 2] + vecPos);\n            indices.push(triangles[i + 2] + vecPos);\n        }\n\n        for (var _i = 0, _j = recPoints.length; _i < _j; _i++) {\n            verts.push(recPoints[_i], recPoints[++_i], r, g, b, alpha);\n        }\n    }\n\n    if (graphicsData.lineWidth) {\n        var tempPoints = graphicsData.points;\n\n        graphicsData.points = recPoints;\n\n        (0, _buildLine2.default)(graphicsData, webGLData, webGLDataNativeLines);\n\n        graphicsData.points = tempPoints;\n    }\n}\n\n/**\n * Calculate a single point for a quadratic bezier curve.\n * Utility function used by quadraticBezierCurve.\n * Ignored from docs since it is not directly exposed.\n *\n * @ignore\n * @private\n * @param {number} n1 - first number\n * @param {number} n2 - second number\n * @param {number} perc - percentage\n * @return {number} the result\n *\n */\nfunction getPt(n1, n2, perc) {\n    var diff = n2 - n1;\n\n    return n1 + diff * perc;\n}\n\n/**\n * Calculate the points for a quadratic bezier curve. (helper function..)\n * Based on: https://stackoverflow.com/questions/785097/how-do-i-implement-a-bezier-curve-in-c\n *\n * Ignored from docs since it is not directly exposed.\n *\n * @ignore\n * @private\n * @param {number} fromX - Origin point x\n * @param {number} fromY - Origin point x\n * @param {number} cpX - Control point x\n * @param {number} cpY - Control point y\n * @param {number} toX - Destination point x\n * @param {number} toY - Destination point y\n * @param {number[]} [out=[]] - The output array to add points into. If not passed, a new array is created.\n * @return {number[]} an array of points\n */\nfunction quadraticBezierCurve(fromX, fromY, cpX, cpY, toX, toY) {\n    var out = arguments.length > 6 && arguments[6] !== undefined ? arguments[6] : [];\n\n    var n = 20;\n    var points = out;\n\n    var xa = 0;\n    var ya = 0;\n    var xb = 0;\n    var yb = 0;\n    var x = 0;\n    var y = 0;\n\n    for (var i = 0, j = 0; i <= n; ++i) {\n        j = i / n;\n\n        // The Green Line\n        xa = getPt(fromX, cpX, j);\n        ya = getPt(fromY, cpY, j);\n        xb = getPt(cpX, toX, j);\n        yb = getPt(cpY, toY, j);\n\n        // The Black Dot\n        x = getPt(xa, xb, j);\n        y = getPt(ya, yb, j);\n\n        points.push(x, y);\n    }\n\n    return points;\n}\n//# sourceMappingURL=buildRoundedRectangle.js.map"},"lineCount":155}},"hash":"a12eef6643ce10e3e3681460205b27a6","cacheData":{"env":{}}}